UnityQuaternion/Quaternion.py
UnityQuaternion/__init__.py
UnityQuaternionPy-0.1.2.dist-info/METADATA
UnityQuaternionPy-0.1.2.dist-info/WHEEL
UnityQuaternionPy-0.1.2.dist-info/top_level.txt
UnityQuaternionPy-0.1.2.dist-info/RECORD
