Metadata-Version: 2.1
Name: UnityQuaternionPy
Version: 0.1.2
Summary: Immitation of UnityEngine.Quaternion in Python
Home-page: https://github.com/konbraphat51/UnityQuaternionPy
Author: konbraphat51
Author-email: konbraphat51@gmail.com
License: MIT License
Keywords: fromscratch,math,quaternion,geometry,rotation,3d,game,Topic :: Multimedia :: Graphics :: 3D Modeling
Classifier: Development Status :: 3 - Alpha
Classifier: License :: OSI Approved :: MIT License
Classifier: Topic :: Games/Entertainment
Classifier: Topic :: Multimedia :: Graphics :: Editors :: Vector-Based
Classifier: Topic :: Scientific/Engineering
Classifier: Topic :: Scientific/Engineering :: Mathematics
Classifier: Topic :: Utilities
Requires-Python: >=3.8
